CHANGES.rst
DESCRIPTION.rst
LICENSE
MANIFEST.in
README.md
setup.py
src/simops/__init__.py
src/simops/_flip.py
src/simops/_io.py
src/simops/_resize.py
src/simops/_rotate.py
src/simops/_utils.py
src/simple_image_ops.egg-info/PKG-INFO
src/simple_image_ops.egg-info/SOURCES.txt
src/simple_image_ops.egg-info/dependency_links.txt
src/simple_image_ops.egg-info/requires.txt
src/simple_image_ops.egg-info/top_level.txt